astrobject/__init__.py
astrobject/astrometry.py
astrobject/baseobject.py
astrobject/collection.py
astrobject/photometry.py
astrobject/catalogue/__init__.py
astrobject/catalogue/basecatalogue.py
astrobject/catalogue/catalogues.py
astrobject/collections/__init__.py
astrobject/collections/photodiagnostics.py
astrobject/collections/photospatial.py
astrobject/instruments/__init__.py
astrobject/instruments/baseinstrument.py
astrobject/instruments/galex.py
astrobject/instruments/hst.py
astrobject/instruments/instrument.py
astrobject/instruments/panstarrs.py
astrobject/instruments/ptf.py
astrobject/instruments/sdss.py
astrobject/instruments/snifs.py
astrobject/instruments/twomass.py
astrobject/instruments/wise.py
astrobject/instruments/ztf.py
astrobject/utils/__init__.py
astrobject/utils/decorators.py
astrobject/utils/io.py
astrobject/utils/mpladdon.py
astrobject/utils/random.py
astrobject/utils/shape.py
astrobject/utils/statbox.py
astrobject/utils/tools.py
astrobject-0.11.0.dist-info/METADATA
astrobject-0.11.0.dist-info/WHEEL
astrobject-0.11.0.dist-info/top_level.txt
astrobject-0.11.0.dist-info/RECORD
