Metadata-Version: 2.1
Name: astrobject
Version: 0.11.0
Summary: astrobject: Basic tools for astrophysics and cosmology
Home-page: https://github.com/MickaelRigault/astrobject/
Download-URL: https://github.com/MickaelRigault/astrobject/tarball/0.11
Author: Astrobject Developers
Author-email: mrigault@physik.hu-berlin.de
Maintainer: Mickael Rigault
Maintainer-email: mrigault@physik.hu-berlin.de
License: BSD (3-clause)
Classifier: Intended Audience :: Science/Research
Classifier: Programming Language :: Python :: 2.7
Classifier: Programming Language :: Python :: 3.5
Classifier: License :: OSI Approved :: BSD License
Classifier: Topic :: Scientific/Engineering :: Astronomy
Classifier: Operating System :: POSIX
Classifier: Operating System :: Unix
Classifier: Operating System :: MacOS
Requires-Dist: propobject
Requires-Dist: astropy
Requires-Dist: sep
